{
    "pokedex": {
        "pokemon": [
            {
                "attribute": {
                    "number": "29",
                    "name": "Nidoran♀"
                },
                "description": [
                    {
                        "key": "While it does not prefer to fight, even one drop of the poison it secretes from barbs can be fatal.",
                        "attribute": {
                            "rank": "0"
                        }
                    }
                ],
                "genders": [
                    "Female"
                ],
                "species": [
                    "Poison Pin"
                ],
                "evolution": [
                    {
                        "key": "29,30,31",
                        "attribute": {
                            "pattern": "5",
                            "position": "0"
                        }
                    }
                ],
                "formes": [
                    {
                        "forme": [
                            {
                                "attribute": {
                                    "name": "Nidoran♀",
                                    "index": "0"
                                },
                                "images": [
                                    ""
                                ],
                                "stats": [
                                    {
                                        "attribute": {
                                            "hp": "40",
                                            "attack": "40",
                                            "defense": "40",
                                            "specAttack": " 40",
                                            "specDefense": "20",
                                            "speed": "40"
                                        }
                                    }
                                ],
                                "types": [
                                    "Poison"
                                ],
                                "abilities": [
                                    "Poison Point,Rivalry"
                                ],
                                "weakness": [
                                    {
                                        "attribute": {
                                            "type": "Ground",
                                            "mod": "0"
                                        }
                                    },
                                    {
                                        "attribute": {
                                            "type": "Psychic",
                                            "mod": "0"
                                        }
                                    }
                                ],
                                "height": [
                                    "0.4"
                                ],
                                "weight": [
                                    "7.0"
                                ],
                                "formatted-height": [
                                    "0.4 m"
                                ],
                                "formatted-weight": [
                                    "7.0 kg"
                                ]
                            }
                        ]
                    }
                ]
            }
        ]
    }
}