{
    "pokedex": {
        "pokemon": [
            {
                "attribute": {
                    "number": "418",
                    "name": "Buizel"
                },
                "description": [
                    {
                        "key": "It spins its two tails like a screw to propel itself through water. The tails also slice clinging seaweed.",
                        "attribute": {
                            "rank": "0"
                        }
                    }
                ],
                "genders": [
                    "Male,Female"
                ],
                "species": [
                    "Sea Weasel"
                ],
                "evolution": [
                    {
                        "key": "418,419",
                        "attribute": {
                            "pattern": "2",
                            "position": "0"
                        }
                    }
                ],
                "formes": [
                    {
                        "forme": [
                            {
                                "attribute": {
                                    "name": "Buizel",
                                    "index": "0"
                                },
                                "images": [
                                    ""
                                ],
                                "stats": [
                                    {
                                        "attribute": {
                                            "hp": "40",
                                            "attack": "60",
                                            "defense": "40",
                                            "specAttack": " 60",
                                            "specDefense": "20",
                                            "speed": "80"
                                        }
                                    }
                                ],
                                "types": [
                                    "Water"
                                ],
                                "abilities": [
                                    "Swift Swim"
                                ],
                                "weakness": [
                                    {
                                        "attribute": {
                                            "type": "Electric",
                                            "mod": "0"
                                        }
                                    },
                                    {
                                        "attribute": {
                                            "type": "Grass",
                                            "mod": "0"
                                        }
                                    }
                                ],
                                "height": [
                                    "0.7"
                                ],
                                "weight": [
                                    "29.5"
                                ],
                                "formatted-height": [
                                    "0.7 m"
                                ],
                                "formatted-weight": [
                                    "29.5 kg"
                                ]
                            }
                        ]
                    }
                ]
            }
        ]
    }
}