{
    "pokedex": {
        "pokemon": [
            {
                "attribute": {
                    "number": "253",
                    "name": "Grovyle"
                },
                "description": [
                    {
                        "key": "It lives in dense jungles. While  closing in on its prey, it leaps from branch to branch.",
                        "attribute": {
                            "rank": "0"
                        }
                    }
                ],
                "genders": [
                    "Male,Female"
                ],
                "species": [
                    "Wood Gecko"
                ],
                "evolution": [
                    {
                        "key": "252,253,254",
                        "attribute": {
                            "pattern": "5",
                            "position": "1"
                        }
                    }
                ],
                "formes": [
                    {
                        "forme": [
                            {
                                "attribute": {
                                    "name": "Grovyle",
                                    "index": "0"
                                },
                                "images": [
                                    ""
                                ],
                                "stats": [
                                    {
                                        "attribute": {
                                            "hp": "40",
                                            "attack": "60",
                                            "defense": "40",
                                            "specAttack": " 80",
                                            "specDefense": "40",
                                            "speed": "80"
                                        }
                                    }
                                ],
                                "types": [
                                    "Grass"
                                ],
                                "abilities": [
                                    "Overgrow"
                                ],
                                "weakness": [
                                    {
                                        "attribute": {
                                            "type": "Bug",
                                            "mod": "0"
                                        }
                                    },
                                    {
                                        "attribute": {
                                            "type": "Fire",
                                            "mod": "0"
                                        }
                                    },
                                    {
                                        "attribute": {
                                            "type": "Flying",
                                            "mod": "0"
                                        }
                                    },
                                    {
                                        "attribute": {
                                            "type": "Ice",
                                            "mod": "0"
                                        }
                                    },
                                    {
                                        "attribute": {
                                            "type": "Poison",
                                            "mod": "0"
                                        }
                                    }
                                ],
                                "height": [
                                    "0.9"
                                ],
                                "weight": [
                                    "21.6"
                                ],
                                "formatted-height": [
                                    "0.9 m"
                                ],
                                "formatted-weight": [
                                    "21.6 kg"
                                ]
                            }
                        ]
                    }
                ]
            }
        ]
    }
}